LICENSE
MANIFEST.in
README.rst
pyproject.toml
setup.py
pylock/__init__.py
pylock.egg-info/PKG-INFO
pylock.egg-info/SOURCES.txt
pylock.egg-info/dependency_links.txt
pylock.egg-info/not-zip-safe
pylock.egg-info/requires.txt
pylock.egg-info/top_level.txt
pylock/backends/__init__.py
pylock/backends/open_lock/__init__.py
pylock/backends/redis_lock/__init__.py
pylock/tests/__init__.py
pylock/tests/test_backends.py
pylock/tests/test_lock.py