Metadata-Version: 1.1
Name: pylock
Version: 0.4
Summary: Python Distributed Lock
Home-page: http://github.com/waveaccounting/pylock
Author: Nathan Duthoit
Author-email: nathan@waveapps.com
License: BSD
Keywords: lock redis
Platform: UNKNOWN
Classifier: Intended Audience :: Developers
Classifier: Programming Language :: Python
Classifier: Programming Language :: Python :: 2.7
Classifier: Programming Language :: Python :: 3.7
